{
	"credit": "Made with Blockbench",
	"texture_size": [64, 64],
	"textures": {
		"0": "item/custom/sky/pickaxe",
		"particle": "item/custom/sky/pickaxe"
	},
	"elements": [
		{
			"name": "Handle",
			"from": [5, 0, 5],
			"to": [10, 30, 10],
			"faces": {
				"north": {"uv": [1.25, 8.5, 2.5, 16], "texture": "#0"},
				"east": {"uv": [0, 8.5, 1.25, 16], "texture": "#0"},
				"south": {"uv": [3.75, 8.5, 5, 16], "texture": "#0"},
				"west": {"uv": [2.5, 8.5, 3.75, 16], "texture": "#0"},
				"up": {"uv": [2.5, 8.5, 1.25, 7.25], "texture": "#0"},
				"down": {"uv": [3.75, 7.25, 2.5, 8.5], "texture": "#0"}
			}
		},
		{
			"name": "Head",
			"from": [-10.75534, 17.50569, 6.8],
			"to": [-7.35534, 20.90569, 8.2],
			"rotation": {"angle": 0, "axis": "y", "origin": [-9.05534, 19.20569, 8]},
			"faces": {
				"north": {"uv": [9.5, 0.25, 10.25, 1], "texture": "#0"},
				"east": {"uv": [9.25, 0.25, 9.5, 1], "texture": "#0"},
				"south": {"uv": [10.5, 0.25, 11.25, 1], "texture": "#0"},
				"west": {"uv": [10.25, 0.25, 10.5, 1], "texture": "#0"},
				"up": {"uv": [10.25, 0.25, 9.5, 0], "texture": "#0"},
				"down": {"uv": [11, 0, 10.25, 0.25], "texture": "#0"}
			}
		},
		{
			"name": "Head",
			"from": [13.42597, 21.11418, 5],
			"to": [21.42597, 27.11418, 10],
			"rotation": {"angle": -22.5, "axis": "z", "origin": [17.42597, 24.11418, 8]},
			"faces": {
				"north": {"uv": [1.25, 4.75, 3.25, 6.25], "texture": "#0"},
				"east": {"uv": [0, 4.75, 1.25, 6.25], "texture": "#0"},
				"south": {"uv": [4.5, 4.75, 6.5, 6.25], "texture": "#0"},
				"west": {"uv": [3.25, 4.75, 4.5, 6.25], "texture": "#0"},
				"up": {"uv": [3.25, 4.75, 1.25, 3.5], "texture": "#0"},
				"down": {"uv": [5.25, 3.5, 3.25, 4.75], "texture": "#0"}
			}
		},
		{
			"name": "Head",
			"from": [19.28758, 18.47346, 6],
			"to": [25.28758, 23.47346, 9],
			"rotation": {"angle": -45, "axis": "z", "origin": [22.28758, 20.97346, 8]},
			"faces": {
				"north": {"uv": [7.25, 4.25, 8.75, 5.5], "texture": "#0"},
				"east": {"uv": [6.5, 4.25, 7.25, 5.5], "texture": "#0"},
				"south": {"uv": [9.5, 4.25, 11, 5.5], "texture": "#0"},
				"west": {"uv": [8.75, 4.25, 9.5, 5.5], "texture": "#0"},
				"up": {"uv": [8.75, 4.25, 7.25, 3.5], "texture": "#0"},
				"down": {"uv": [10.25, 3.5, 8.75, 4.25], "texture": "#0"}
			}
		},
		{
			"name": "Head",
			"from": [22.35534, 17.50569, 6.8],
			"to": [25.75534, 20.90569, 8.2],
			"rotation": {"angle": 0, "axis": "y", "origin": [25.05534, 19.20569, 8]},
			"faces": {
				"north": {"uv": [9.5, 0.25, 10.25, 1], "texture": "#0"},
				"east": {"uv": [9.25, 0.25, 9.5, 1], "texture": "#0"},
				"south": {"uv": [10.5, 0.25, 11.25, 1], "texture": "#0"},
				"west": {"uv": [10.25, 0.25, 10.5, 1], "texture": "#0"},
				"up": {"uv": [10.25, 0.25, 9.5, 0], "texture": "#0"},
				"down": {"uv": [11, 0, 10.25, 0.25], "texture": "#0"}
			}
		},
		{
			"name": "Head",
			"from": [-7, 21, 5],
			"to": [1, 27, 10],
			"rotation": {"angle": 22.5, "axis": "z", "origin": [-3, 25.5, 8]},
			"faces": {
				"north": {"uv": [1.25, 4.75, 3.25, 6.25], "texture": "#0"},
				"east": {"uv": [0, 4.75, 1.25, 6.25], "texture": "#0"},
				"south": {"uv": [4.5, 4.75, 6.5, 6.25], "texture": "#0"},
				"west": {"uv": [3.25, 4.75, 4.5, 6.25], "texture": "#0"},
				"up": {"uv": [3.25, 4.75, 1.25, 3.5], "texture": "#0"},
				"down": {"uv": [5.25, 3.5, 3.25, 4.75], "texture": "#0"}
			}
		},
		{
			"name": "Head",
			"from": [-10.70179, 17.47346, 6],
			"to": [-4.70179, 22.47346, 9],
			"rotation": {"angle": 45, "axis": "z", "origin": [-8.70179, 20.97346, 8]},
			"faces": {
				"north": {"uv": [7.25, 4.25, 8.75, 5.5], "texture": "#0"},
				"east": {"uv": [6.5, 4.25, 7.25, 5.5], "texture": "#0"},
				"south": {"uv": [9.5, 4.25, 11, 5.5], "texture": "#0"},
				"west": {"uv": [8.75, 4.25, 9.5, 5.5], "texture": "#0"},
				"up": {"uv": [8.75, 4.25, 7.25, 3.5], "texture": "#0"},
				"down": {"uv": [10.25, 3.5, 8.75, 4.25], "texture": "#0"}
			}
		},
		{
			"name": "Head",
			"from": [0, 22, 4],
			"to": [15, 29, 11],
			"faces": {
				"north": {"uv": [1.75, 1.75, 5.5, 3.5], "texture": "#0"},
				"east": {"uv": [0, 1.75, 1.75, 3.5], "texture": "#0"},
				"south": {"uv": [7.25, 1.75, 11, 3.5], "texture": "#0"},
				"west": {"uv": [5.5, 1.75, 7.25, 3.5], "texture": "#0"},
				"up": {"uv": [5.5, 1.75, 1.75, 0], "texture": "#0"},
				"down": {"uv": [9.25, 0, 5.5, 1.75], "texture": "#0"}
			}
		},
		{
			"from": [6, 24, 10],
			"to": [9, 27, 12],
			"rotation": {"angle": 0, "axis": "y", "origin": [8, 25.5, 12]},
			"faces": {
				"north": {"uv": [8.5, 14.25, 9.25, 15], "texture": "#0"},
				"east": {"uv": [8, 14.25, 8.5, 15], "texture": "#0"},
				"south": {"uv": [9.75, 14.25, 10.5, 15], "texture": "#0"},
				"west": {"uv": [9.25, 14.25, 9.75, 15], "texture": "#0"},
				"up": {"uv": [9.25, 14.25, 8.5, 13.75], "texture": "#0"},
				"down": {"uv": [10, 13.75, 9.25, 14.25], "texture": "#0"}
			}
		},
		{
			"from": [6, 24, 3],
			"to": [9, 27, 5],
			"rotation": {"angle": 0, "axis": "y", "origin": [8, 25.5, 12]},
			"faces": {
				"north": {"uv": [8.5, 14.25, 9.25, 15], "texture": "#0"},
				"east": {"uv": [8, 14.25, 8.5, 15], "texture": "#0"},
				"south": {"uv": [9.75, 14.25, 10.5, 15], "texture": "#0"},
				"west": {"uv": [9.25, 14.25, 9.75, 15], "texture": "#0"},
				"up": {"uv": [9.25, 14.25, 8.5, 13.75], "texture": "#0"},
				"down": {"uv": [10, 13.75, 9.25, 14.25], "texture": "#0"}
			}
		},
		{
			"from": [5.999, 22.999, 2.999],
			"to": [9.001, 25.001, 5.001],
			"rotation": {"angle": -45, "axis": "x", "origin": [8, 24, 4]},
			"faces": {
				"north": {"uv": [8.5, 15.5, 9.25, 16], "texture": "#0"},
				"east": {"uv": [8, 15.5, 8.5, 16], "texture": "#0"},
				"south": {"uv": [9.75, 15.5, 10.5, 16], "texture": "#0"},
				"west": {"uv": [9.25, 15.5, 9.75, 16], "texture": "#0"},
				"up": {"uv": [9.25, 15.5, 8.5, 15], "texture": "#0"},
				"down": {"uv": [10, 15, 9.25, 15.5], "texture": "#0"}
			}
		},
		{
			"from": [5.999, 25.999, 2.999],
			"to": [9.001, 28.001, 5.001],
			"rotation": {"angle": -45, "axis": "x", "origin": [8, 27, 4]},
			"faces": {
				"north": {"uv": [8.5, 15.5, 9.25, 16], "texture": "#0"},
				"east": {"uv": [8, 15.5, 8.5, 16], "texture": "#0"},
				"south": {"uv": [9.75, 15.5, 10.5, 16], "texture": "#0"},
				"west": {"uv": [9.25, 15.5, 9.75, 16], "texture": "#0"},
				"up": {"uv": [9.25, 15.5, 8.5, 15], "texture": "#0"},
				"down": {"uv": [10, 15, 9.25, 15.5], "texture": "#0"}
			}
		},
		{
			"from": [5.999, 22.999, 9.999],
			"to": [9.001, 25.001, 12.001],
			"rotation": {"angle": -45, "axis": "x", "origin": [7.5, 24, 11]},
			"faces": {
				"north": {"uv": [8.5, 15.5, 9.25, 16], "texture": "#0"},
				"east": {"uv": [8, 15.5, 8.5, 16], "texture": "#0"},
				"south": {"uv": [9.75, 15.5, 10.5, 16], "texture": "#0"},
				"west": {"uv": [9.25, 15.5, 9.75, 16], "texture": "#0"},
				"up": {"uv": [9.25, 15.5, 8.5, 15], "texture": "#0"},
				"down": {"uv": [10, 15, 9.25, 15.5], "texture": "#0"}
			}
		},
		{
			"from": [5.999, 25.999, 9.999],
			"to": [9.001, 28.001, 12.001],
			"rotation": {"angle": -45, "axis": "x", "origin": [7.5, 27, 11]},
			"faces": {
				"north": {"uv": [8.5, 15.5, 9.25, 16], "texture": "#0"},
				"east": {"uv": [8, 15.5, 8.5, 16], "texture": "#0"},
				"south": {"uv": [9.75, 15.5, 10.5, 16], "texture": "#0"},
				"west": {"uv": [9.25, 15.5, 9.75, 16], "texture": "#0"},
				"up": {"uv": [9.25, 15.5, 8.5, 15], "texture": "#0"},
				"down": {"uv": [10, 15, 9.25, 15.5], "texture": "#0"}
			}
		},
		{
			"from": [8.8, -0.2, 4.8],
			"to": [10.2, 22.2, 6.2],
			"faces": {
				"north": {"uv": [15.25, 10.5, 15.5, 16], "texture": "#0"},
				"east": {"uv": [15, 10.5, 15.25, 16], "texture": "#0"},
				"south": {"uv": [15.75, 10.5, 16, 16], "texture": "#0"},
				"west": {"uv": [15.5, 10.5, 15.75, 16], "texture": "#0"},
				"up": {"uv": [15.5, 10.5, 15.25, 10.25], "texture": "#0"},
				"down": {"uv": [15.75, 10.25, 15.5, 10.5], "texture": "#0"}
			}
		},
		{
			"from": [4.8, -0.2, 4.8],
			"to": [6.2, 22.2, 6.2],
			"faces": {
				"north": {"uv": [15.25, 10.5, 15.5, 16], "texture": "#0"},
				"east": {"uv": [15, 10.5, 15.25, 16], "texture": "#0"},
				"south": {"uv": [15.75, 10.5, 16, 16], "texture": "#0"},
				"west": {"uv": [15.5, 10.5, 15.75, 16], "texture": "#0"},
				"up": {"uv": [15.5, 10.5, 15.25, 10.25], "texture": "#0"},
				"down": {"uv": [15.75, 10.25, 15.5, 10.5], "texture": "#0"}
			}
		},
		{
			"from": [4.8, -0.2, 8.8],
			"to": [6.2, 22.2, 10.2],
			"faces": {
				"north": {"uv": [15.25, 10.5, 15.5, 16], "texture": "#0"},
				"east": {"uv": [15, 10.5, 15.25, 16], "texture": "#0"},
				"south": {"uv": [15.75, 10.5, 16, 16], "texture": "#0"},
				"west": {"uv": [15.5, 10.5, 15.75, 16], "texture": "#0"},
				"up": {"uv": [15.5, 10.5, 15.25, 10.25], "texture": "#0"},
				"down": {"uv": [15.75, 10.25, 15.5, 10.5], "texture": "#0"}
			}
		},
		{
			"from": [8.8, -0.2, 8.8],
			"to": [10.2, 22.2, 10.2],
			"faces": {
				"north": {"uv": [15.25, 10.5, 15.5, 16], "texture": "#0"},
				"east": {"uv": [15, 10.5, 15.25, 16], "texture": "#0"},
				"south": {"uv": [15.75, 10.5, 16, 16], "texture": "#0"},
				"west": {"uv": [15.5, 10.5, 15.75, 16], "texture": "#0"},
				"up": {"uv": [15.5, 10.5, 15.25, 10.25], "texture": "#0"},
				"down": {"uv": [15.75, 10.25, 15.5, 10.5], "texture": "#0"}
			}
		}
	],
	"display": {
		"thirdperson_righthand": {
			"rotation": [0, 90, 0],
			"translation": [0.25, 2.25, 1],
			"scale": [0.3, 0.3, 0.3]
		},
		"thirdperson_lefthand": {
			"rotation": [0, 90, 0],
			"translation": [0.25, 2.25, 1.5],
			"scale": [0.3, 0.3, 0.3]
		},
		"firstperson_righthand": {
			"rotation": [0, 90, 0],
			"scale": [0.3, 0.3, 0.3]
		},
		"firstperson_lefthand": {
			"rotation": [0, 90, 0],
			"scale": [0.3, 0.3, 0.3]
		},
		"ground": {
			"rotation": [0, 0, 55],
			"translation": [0, 4.5, 0]
		},
		"gui": {
			"translation": [0, -2.5, 0],
			"scale": [0.4, 0.4, 0.4]
		},
		"head": {
			"translation": [0, -9.75, 0],
			"scale": [1, 1, 0.9]
		},
		"fixed": {
			"translation": [0, -2.5, 0.25],
			"scale": [0.4, 0.4, 0.41]
		}
	},
	"groups": [
		0,
		{
			"name": "Head",
			"origin": [8, 8, 8],
			"color": 0,
			"children": [1, 2, 3, 4, 5, 6, 7]
		},
		{
			"name": "Crystal",
			"origin": [8, 8, 8],
			"color": 0,
			"children": [8, 9, 10, 11, 12, 13]
		},
		14,
		15,
		16,
		17
	]
}